nerrds/__init__.py
nerrds/bme.py
nerrds/functions.py
nerrds/gen_conf.py
nerrds/nerrds.py
nerrds/refine.py
nerrds/reweight_bme.py
nerrds/run_ansurr.py
nerrds/scripts/__init__.py
nerrds/scripts/AMBER/__init__.py
nerrds/scripts/AMBER/extract_pdb.cpptraj
nerrds/scripts/AMBER/leap.in
nerrds/scripts/AMBER/min.in
nerrds/scripts/AMBER/min_solv.in
nerrds/scripts/BME/BME.py
nerrds/scripts/BME/BME_tools.py
nerrds/scripts/BME/__init__.py
nerrds-0.0.106.dist-info/LICENSE
nerrds-0.0.106.dist-info/METADATA
nerrds-0.0.106.dist-info/WHEEL
nerrds-0.0.106.dist-info/entry_points.txt
nerrds-0.0.106.dist-info/top_level.txt
nerrds-0.0.106.dist-info/RECORD
