Metadata-Version: 2.1
Name: nerrds
Version: 0.0.106
Summary: NERRDS uses backbone chemical shifts to generate an ensemble
Home-page: https://github.com/nickjf/nerrds
Author: Nick J Fowler
Author-email: nickjfowler0@gmail.com
Project-URL: Bug Tracker, https://github.com/nickjf/nerrds/issues
Classifier: Programming Language :: Python :: 3
Classifier: License :: OSI Approved :: MIT License
Classifier: Operating System :: OS Independent
Requires-Python: >=3.6
License-File: LICENSE
Requires-Dist: numpy (>=1.18.5)
Requires-Dist: ansurr (>=2.1.2)
Requires-Dist: pandas
Requires-Dist: scikit-learn
Requires-Dist: prody
Requires-Dist: pdb-tools
